LICENSE
README.md
setup.py
kalshi_client/__init__.py
kalshi_client/client.py
kalshi_client/utils.py
kalshi_client.egg-info/PKG-INFO
kalshi_client.egg-info/SOURCES.txt
kalshi_client.egg-info/dependency_links.txt
kalshi_client.egg-info/requires.txt
kalshi_client.egg-info/top_level.txt