Metadata-Version: 2.1
Name: kalshi-client
Version: 0.1.3
Summary: An unofficial python client for the Kalshi API
Home-page: https://github.com/vaguenebula/kalshi-client
Author: vaguenebula
Author-email: nebbylockedin@gmail.com
Classifier: Programming Language :: Python :: 3
Classifier: License :: OSI Approved :: MIT License
Classifier: Operating System :: OS Independent
Requires-Python: >=3.6
License-File: LICENSE
